ttwhy/__init__.py
ttwhy/__main__.py
ttwhy/character.py
ttwhy/color.py
ttwhy/main.py
ttwhy/terminal.py
ttwhy/util/__init__.py
ttwhy/util/ensure_iverilog.py
ttwhy/util/helper_types.py
ttwhy/vendored/MxPlus_IBM_VGA_8x16.ttf
ttwhy/vendored/MxPlus_IBM_VGA_8x16_LICENSE
ttwhy/vendored/__init__.py
ttwhy/vendored/iverilog-v12-20220611-x64_setup.exe
ttwhy/vendored/iverilog_LICENSE
ttwhy-0.1.0.dist-info/METADATA
ttwhy-0.1.0.dist-info/WHEEL
ttwhy-0.1.0.dist-info/entry_points.txt
ttwhy-0.1.0.dist-info/licenses/ttwhy/vendored/MxPlus_IBM_VGA_8x16_LICENSE
ttwhy-0.1.0.dist-info/licenses/ttwhy/vendored/iverilog_LICENSE
ttwhy-0.1.0.dist-info/RECORD
